md_link_checker.py
md_link_checker-1.10.dist-info/METADATA
md_link_checker-1.10.dist-info/WHEEL
md_link_checker-1.10.dist-info/entry_points.txt
md_link_checker-1.10.dist-info/top_level.txt
md_link_checker-1.10.dist-info/RECORD
