Metadata-Version: 2.4
Name: md-link-checker
Version: 1.10
Summary: Utility to check url, section reference, and path links in Markdown files
Author-email: Mark Blakeney <mark.blakeney@bullet-systems.net>
License-Expression: GPL-3.0-or-later
Project-URL: Homepage, https://github.com/bulletmark/md-link-checker
Keywords: markdown,github,gfm
Classifier: Programming Language :: Python :: 3
Requires-Python: >=3.9
Requires-Dist: aiohttp
